[
  {
    "household_id": "large_family_luxury",
    "household_type": "large_family",
    "wealth": "luxury",
    "day": 1,
    "solar_kwh": 4.21,
    "load_kwh": 79.73,
    "import_kwh": 75.51,
    "export_kwh": 0.0,
    "self_consumed_kwh": 4.21
  },
  {
    "household_id": "large_family_luxury",
    "household_type": "large_family",
    "wealth": "luxury",
    "day": 2,
    "solar_kwh": 17.32,
    "load_kwh": 77.44,
    "import_kwh": 62.2,
    "export_kwh": 2.08,
    "self_consumed_kwh": 15.24
  },
  {
    "household_id": "large_family_luxury",
    "household_type": "large_family",
    "wealth": "luxury",
    "day": 3,
    "solar_kwh": 15.3,
    "load_kwh": 75.6,
    "import_kwh": 61.63,
    "export_kwh": 1.33,
    "self_consumed_kwh": 13.97
  },
  {
    "household_id": "large_family_luxury",
    "household_type": "large_family",
    "wealth": "luxury",
    "day": 4,
    "solar_kwh": 7.85,
    "load_kwh": 67.99,
    "import_kwh": 60.14,
    "export_kwh": 0.0,
    "self_consumed_kwh": 7.85
  },
  {
    "household_id": "large_family_luxury",
    "household_type": "large_family",
    "wealth": "luxury",
    "day": 5,
    "solar_kwh": 7.81,
    "load_kwh": 64.86,
    "import_kwh": 57.05,
    "export_kwh": 0.0,
    "self_consumed_kwh": 7.81
  },
  {
    "household_id": "large_family_luxury",
    "household_type": "large_family",
    "wealth": "luxury",
    "day": 6,
    "solar_kwh": 10.66,
    "load_kwh": 61.28,
    "import_kwh": 50.8,
    "export_kwh": 0.18,
    "self_consumed_kwh": 10.48
  },
  {
    "household_id": "large_family_luxury",
    "household_type": "large_family",
    "wealth": "luxury",
    "day": 7,
    "solar_kwh": 7.37,
    "load_kwh": 78.56,
    "import_kwh": 71.2,
    "export_kwh": 0.0,
    "self_consumed_kwh": 7.37
  },
  {
    "household_id": "large_family_luxury",
    "household_type": "large_family",
    "wealth": "luxury",
    "day": 8,
    "solar_kwh": 27.96,
    "load_kwh": 72.45,
    "import_kwh": 56.44,
    "export_kwh": 11.95,
    "self_consumed_kwh": 16.01
  },
  {
    "household_id": "large_family_luxury",
    "household_type": "large_family",
    "wealth": "luxury",
    "day": 9,
    "solar_kwh": 8.26,
    "load_kwh": 70.82,
    "import_kwh": 62.57,
    "export_kwh": 0.0,
    "self_consumed_kwh": 8.26
  },
  {
    "household_id": "large_family_luxury",
    "household_type": "large_family",
    "wealth": "luxury",
    "day": 10,
    "solar_kwh": 19.9,
    "load_kwh": 68.47,
    "import_kwh": 52.14,
    "export_kwh": 3.58,
    "self_consumed_kwh": 16.32
  },
  {
    "household_id": "large_family_luxury",
    "household_type": "large_family",
    "wealth": "luxury",
    "day": 11,
    "solar_kwh": 8.44,
    "load_kwh": 62.52,
    "import_kwh": 54.08,
    "export_kwh": 0.0,
    "self_consumed_kwh": 8.44
  },
  {
    "household_id": "large_family_luxury",
    "household_type": "large_family",
    "wealth": "luxury",
    "day": 12,
    "solar_kwh": 18.92,
    "load_kwh": 56.86,
    "import_kwh": 43.34,
    "export_kwh": 5.4,
    "self_consumed_kwh": 13.52
  },
  {
    "household_id": "large_family_luxury",
    "household_type": "large_family",
    "wealth": "luxury",
    "day": 13,
    "solar_kwh": 4.01,
    "load_kwh": 63.37,
    "import_kwh": 59.36,
    "export_kwh": 0.0,
    "self_consumed_kwh": 4.01
  },
  {
    "household_id": "large_family_luxury",
    "household_type": "large_family",
    "wealth": "luxury",
    "day": 14,
    "solar_kwh": 3.93,
    "load_kwh": 82.7,
    "import_kwh": 78.77,
    "export_kwh": 0.0,
    "self_consumed_kwh": 3.93
  },
  {
    "household_id": "large_family_luxury",
    "household_type": "large_family",
    "wealth": "luxury",
    "day": 15,
    "solar_kwh": 5.19,
    "load_kwh": 65.69,
    "import_kwh": 60.5,
    "export_kwh": 0.0,
    "self_consumed_kwh": 5.19
  },
  {
    "household_id": "large_family_luxury",
    "household_type": "large_family",
    "wealth": "luxury",
    "day": 16,
    "solar_kwh": 16.89,
    "load_kwh": 75.12,
    "import_kwh": 60.86,
    "export_kwh": 2.62,
    "self_consumed_kwh": 14.26
  },
  {
    "household_id": "large_family_luxury",
    "household_type": "large_family",
    "wealth": "luxury",
    "day": 17,
    "solar_kwh": 33.49,
    "load_kwh": 76.31,
    "import_kwh": 58.11,
    "export_kwh": 15.29,
    "self_consumed_kwh": 18.2
  },
  {
    "household_id": "large_family_luxury",
    "household_type": "large_family",
    "wealth": "luxury",
    "day": 18,
    "solar_kwh": 20.13,
    "load_kwh": 74.52,
    "import_kwh": 59.25,
    "export_kwh": 4.86,
    "self_consumed_kwh": 15.27
  },
  {
    "household_id": "large_family_luxury",
    "household_type": "large_family",
    "wealth": "luxury",
    "day": 19,
    "solar_kwh": 10.51,
    "load_kwh": 55.21,
    "import_kwh": 44.83,
    "export_kwh": 0.13,
    "self_consumed_kwh": 10.38
  },
  {
    "household_id": "large_family_luxury",
    "household_type": "large_family",
    "wealth": "luxury",
    "day": 20,
    "solar_kwh": 12.9,
    "load_kwh": 68.39,
    "import_kwh": 56.04,
    "export_kwh": 0.55,
    "self_consumed_kwh": 12.35
  },
  {
    "household_id": "large_family_luxury",
    "household_type": "large_family",
    "wealth": "luxury",
    "day": 21,
    "solar_kwh": 20.87,
    "load_kwh": 56.55,
    "import_kwh": 42.27,
    "export_kwh": 6.59,
    "self_consumed_kwh": 14.28
  },
  {
    "household_id": "large_family_luxury",
    "household_type": "large_family",
    "wealth": "luxury",
    "day": 22,
    "solar_kwh": 0.77,
    "load_kwh": 73.66,
    "import_kwh": 72.9,
    "export_kwh": 0.0,
    "self_consumed_kwh": 0.77
  },
  {
    "household_id": "large_family_luxury",
    "household_type": "large_family",
    "wealth": "luxury",
    "day": 23,
    "solar_kwh": 10.1,
    "load_kwh": 73.93,
    "import_kwh": 63.85,
    "export_kwh": 0.02,
    "self_consumed_kwh": 10.08
  },
  {
    "household_id": "large_family_luxury",
    "household_type": "large_family",
    "wealth": "luxury",
    "day": 24,
    "solar_kwh": 29.52,
    "load_kwh": 68.09,
    "import_kwh": 51.24,
    "export_kwh": 12.66,
    "self_consumed_kwh": 16.85
  },
  {
    "household_id": "large_family_luxury",
    "household_type": "large_family",
    "wealth": "luxury",
    "day": 25,
    "solar_kwh": 7.54,
    "load_kwh": 85.12,
    "import_kwh": 77.57,
    "export_kwh": 0.0,
    "self_consumed_kwh": 7.54
  },
  {
    "household_id": "large_family_luxury",
    "household_type": "large_family",
    "wealth": "luxury",
    "day": 26,
    "solar_kwh": 13.41,
    "load_kwh": 62.34,
    "import_kwh": 49.88,
    "export_kwh": 0.95,
    "self_consumed_kwh": 12.45
  },
  {
    "household_id": "large_family_luxury",
    "household_type": "large_family",
    "wealth": "luxury",
    "day": 27,
    "solar_kwh": 20.81,
    "load_kwh": 73.7,
    "import_kwh": 58.48,
    "export_kwh": 5.59,
    "self_consumed_kwh": 15.23
  },
  {
    "household_id": "large_family_luxury",
    "household_type": "large_family",
    "wealth": "luxury",
    "day": 28,
    "solar_kwh": 4.89,
    "load_kwh": 82.27,
    "import_kwh": 77.39,
    "export_kwh": 0.0,
    "self_consumed_kwh": 4.89
  },
  {
    "household_id": "large_family_luxury",
    "household_type": "large_family",
    "wealth": "luxury",
    "day": 29,
    "solar_kwh": 20.8,
    "load_kwh": 52.8,
    "import_kwh": 38.58,
    "export_kwh": 6.58,
    "self_consumed_kwh": 14.22
  },
  {
    "household_id": "large_family_luxury",
    "household_type": "large_family",
    "wealth": "luxury",
    "day": 30,
    "solar_kwh": 24.19,
    "load_kwh": 71.27,
    "import_kwh": 56.2,
    "export_kwh": 9.12,
    "self_consumed_kwh": 15.07
  },
  {
    "household_id": "large_family_middle",
    "household_type": "large_family",
    "wealth": "middle",
    "day": 1,
    "solar_kwh": 4.21,
    "load_kwh": 45.61,
    "import_kwh": 36.31,
    "export_kwh": 0.0,
    "self_consumed_kwh": 4.21
  },
  {
    "household_id": "large_family_middle",
    "household_type": "large_family",
    "wealth": "middle",
    "day": 2,
    "solar_kwh": 17.32,
    "load_kwh": 45.21,
    "import_kwh": 29.44,
    "export_kwh": 0.0,
    "self_consumed_kwh": 17.32
  },
  {
    "household_id": "large_family_middle",
    "household_type": "large_family",
    "wealth": "middle",
    "day": 3,
    "solar_kwh": 15.3,
    "load_kwh": 48.9,
    "import_kwh": 34.98,
    "export_kwh": 0.0,
    "self_consumed_kwh": 15.3
  },
  {
    "household_id": "large_family_middle",
    "household_type": "large_family",
    "wealth": "middle",
    "day": 4,
    "solar_kwh": 7.85,
    "load_kwh": 46.17,
    "import_kwh": 39.03,
    "export_kwh": 0.0,
    "self_consumed_kwh": 7.85
  },
  {
    "household_id": "large_family_middle",
    "household_type": "large_family",
    "wealth": "middle",
    "day": 5,
    "solar_kwh": 7.81,
    "load_kwh": 44.45,
    "import_kwh": 37.35,
    "export_kwh": 0.0,
    "self_consumed_kwh": 7.81
  },
  {
    "household_id": "large_family_middle",
    "household_type": "large_family",
    "wealth": "middle",
    "day": 6,
    "solar_kwh": 10.66,
    "load_kwh": 49.05,
    "import_kwh": 39.35,
    "export_kwh": 0.0,
    "self_consumed_kwh": 10.66
  },
  {
    "household_id": "large_family_middle",
    "household_type": "large_family",
    "wealth": "middle",
    "day": 7,
    "solar_kwh": 7.37,
    "load_kwh": 40.16,
    "import_kwh": 33.46,
    "export_kwh": 0.0,
    "self_consumed_kwh": 7.37
  },
  {
    "household_id": "large_family_middle",
    "household_type": "large_family",
    "wealth": "middle",
    "day": 8,
    "solar_kwh": 27.96,
    "load_kwh": 41.18,
    "import_kwh": 16.88,
    "export_kwh": 1.52,
    "self_consumed_kwh": 26.43
  },
  {
    "household_id": "large_family_middle",
    "household_type": "large_family",
    "wealth": "middle",
    "day": 9,
    "solar_kwh": 8.26,
    "load_kwh": 43.78,
    "import_kwh": 36.26,
    "export_kwh": 0.0,
    "self_consumed_kwh": 8.26
  },
  {
    "household_id": "large_family_middle",
    "household_type": "large_family",
    "wealth": "middle",
    "day": 10,
    "solar_kwh": 19.9,
    "load_kwh": 34.24,
    "import_kwh": 16.13,
    "export_kwh": 0.0,
    "self_consumed_kwh": 19.9
  },
  {
    "household_id": "large_family_middle",
    "household_type": "large_family",
    "wealth": "middle",
    "day": 11,
    "solar_kwh": 8.44,
    "load_kwh": 42.58,
    "import_kwh": 34.9,
    "export_kwh": 0.0,
    "self_consumed_kwh": 8.44
  },
  {
    "household_id": "large_family_middle",
    "household_type": "large_family",
    "wealth": "middle",
    "day": 12,
    "solar_kwh": 18.92,
    "load_kwh": 51.23,
    "import_kwh": 34.01,
    "export_kwh": 0.0,
    "self_consumed_kwh": 18.92
  },
  {
    "household_id": "large_family_middle",
    "household_type": "large_family",
    "wealth": "middle",
    "day": 13,
    "solar_kwh": 4.01,
    "load_kwh": 54.6,
    "import_kwh": 50.96,
    "export_kwh": 0.0,
    "self_consumed_kwh": 4.01
  },
  {
    "household_id": "large_family_middle",
    "household_type": "large_family",
    "wealth": "middle",
    "day": 14,
    "solar_kwh": 3.93,
    "load_kwh": 49.63,
    "import_kwh": 46.06,
    "export_kwh": 0.0,
    "self_consumed_kwh": 3.93
  },
  {
    "household_id": "large_family_middle",
    "household_type": "large_family",
    "wealth": "middle",
    "day": 15,
    "solar_kwh": 5.19,
    "load_kwh": 49.6,
    "import_kwh": 44.87,
    "export_kwh": 0.0,
    "self_consumed_kwh": 5.19
  },
  {
    "household_id": "large_family_middle",
    "household_type": "large_family",
    "wealth": "middle",
    "day": 16,
    "solar_kwh": 16.89,
    "load_kwh": 35.62,
    "import_kwh": 20.25,
    "export_kwh": 0.0,
    "self_consumed_kwh": 16.89
  },
  {
    "household_id": "large_family_middle",
    "household_type": "large_family",
    "wealth": "middle",
    "day": 17,
    "solar_kwh": 33.49,
    "load_kwh": 49.65,
    "import_kwh": 21.63,
    "export_kwh": 3.31,
    "self_consumed_kwh": 30.18
  },
  {
    "household_id": "large_family_middle",
    "household_type": "large_family",
    "wealth": "middle",
    "day": 18,
    "solar_kwh": 20.13,
    "load_kwh": 48.25,
    "import_kwh": 29.93,
    "export_kwh": 0.0,
    "self_consumed_kwh": 20.13
  },
  {
    "household_id": "large_family_middle",
    "household_type": "large_family",
    "wealth": "middle",
    "day": 19,
    "solar_kwh": 10.51,
    "load_kwh": 46.44,
    "import_kwh": 36.87,
    "export_kwh": 0.0,
    "self_consumed_kwh": 10.51
  },
  {
    "household_id": "large_family_middle",
    "household_type": "large_family",
    "wealth": "middle",
    "day": 20,
    "solar_kwh": 12.9,
    "load_kwh": 46.35,
    "import_kwh": 34.6,
    "export_kwh": 0.0,
    "self_consumed_kwh": 12.9
  },
  {
    "household_id": "large_family_middle",
    "household_type": "large_family",
    "wealth": "middle",
    "day": 21,
    "solar_kwh": 20.87,
    "load_kwh": 42.38,
    "import_kwh": 23.39,
    "export_kwh": 0.0,
    "self_consumed_kwh": 20.87
  },
  {
    "household_id": "large_family_middle",
    "household_type": "large_family",
    "wealth": "middle",
    "day": 22,
    "solar_kwh": 7.67,
    "load_kwh": 38.69,
    "import_kwh": 31.71,
    "export_kwh": 0.0,
    "self_consumed_kwh": 7.67
  },
  {
    "household_id": "large_family_middle",
    "household_type": "large_family",
    "wealth": "middle",
    "day": 23,
    "solar_kwh": 10.1,
    "load_kwh": 35.44,
    "import_kwh": 26.25,
    "export_kwh": 0.0,
    "self_consumed_kwh": 10.1
  },
  {
    "household_id": "large_family_middle",
    "household_type": "large_family",
    "wealth": "middle",
    "day": 24,
    "solar_kwh": 29.52,
    "load_kwh": 38.39,
    "import_kwh": 11.82,
    "export_kwh": 0.52,
    "self_consumed_kwh": 29.0
  },
  {
    "household_id": "large_family_middle",
    "household_type": "large_family",
    "wealth": "middle",
    "day": 25,
    "solar_kwh": 7.54,
    "load_kwh": 34.27,
    "import_kwh": 27.41,
    "export_kwh": 0.0,
    "self_consumed_kwh": 7.54
  },
  {
    "household_id": "large_family_middle",
    "household_type": "large_family",
    "wealth": "middle",
    "day": 26,
    "solar_kwh": 13.41,
    "load_kwh": 57.05,
    "import_kwh": 44.85,
    "export_kwh": 0.0,
    "self_consumed_kwh": 13.41
  },
  {
    "household_id": "large_family_middle",
    "household_type": "large_family",
    "wealth": "middle",
    "day": 27,
    "solar_kwh": 20.81,
    "load_kwh": 48.15,
    "import_kwh": 29.2,
    "export_kwh": 0.0,
    "self_consumed_kwh": 20.81
  },
  {
    "household_id": "large_family_middle",
    "household_type": "large_family",
    "wealth": "middle",
    "day": 28,
    "solar_kwh": 4.89,
    "load_kwh": 46.99,
    "import_kwh": 42.55,
    "export_kwh": 0.0,
    "self_consumed_kwh": 4.89
  },
  {
    "household_id": "large_family_middle",
    "household_type": "large_family",
    "wealth": "middle",
    "day": 29,
    "solar_kwh": 20.8,
    "load_kwh": 48.22,
    "import_kwh": 29.3,
    "export_kwh": 0.0,
    "self_consumed_kwh": 20.8
  },
  {
    "household_id": "large_family_middle",
    "household_type": "large_family",
    "wealth": "middle",
    "day": 30,
    "solar_kwh": 24.19,
    "load_kwh": 50.54,
    "import_kwh": 28.53,
    "export_kwh": 0.0,
    "self_consumed_kwh": 24.19
  },
  {
    "household_id": "small_family_high",
    "household_type": "small_family",
    "wealth": "high",
    "day": 1,
    "solar_kwh": 4.21,
    "load_kwh": 30.62,
    "import_kwh": 21.31,
    "export_kwh": 0.0,
    "self_consumed_kwh": 4.21
  },
  {
    "household_id": "small_family_high",
    "household_type": "small_family",
    "wealth": "high",
    "day": 2,
    "solar_kwh": 17.32,
    "load_kwh": 29.06,
    "import_kwh": 13.3,
    "export_kwh": 0.0,
    "self_consumed_kwh": 17.32
  },
  {
    "household_id": "small_family_high",
    "household_type": "small_family",
    "wealth": "high",
    "day": 3,
    "solar_kwh": 15.3,
    "load_kwh": 34.2,
    "import_kwh": 20.27,
    "export_kwh": 0.0,
    "self_consumed_kwh": 15.3
  },
  {
    "household_id": "small_family_high",
    "household_type": "small_family",
    "wealth": "high",
    "day": 4,
    "solar_kwh": 7.85,
    "load_kwh": 25.77,
    "import_kwh": 18.63,
    "export_kwh": 0.0,
    "self_consumed_kwh": 7.85
  },
  {
    "household_id": "small_family_high",
    "household_type": "small_family",
    "wealth": "high",
    "day": 5,
    "solar_kwh": 7.81,
    "load_kwh": 31.54,
    "import_kwh": 24.44,
    "export_kwh": 0.0,
    "self_consumed_kwh": 7.81
  },
  {
    "household_id": "small_family_high",
    "household_type": "small_family",
    "wealth": "high",
    "day": 6,
    "solar_kwh": 10.66,
    "load_kwh": 28.72,
    "import_kwh": 19.01,
    "export_kwh": 0.0,
    "self_consumed_kwh": 10.66
  },
  {
    "household_id": "small_family_high",
    "household_type": "small_family",
    "wealth": "high",
    "day": 7,
    "solar_kwh": 7.37,
    "load_kwh": 25.5,
    "import_kwh": 18.8,
    "export_kwh": 0.0,
    "self_consumed_kwh": 7.37
  },
  {
    "household_id": "small_family_high",
    "household_type": "small_family",
    "wealth": "high",
    "day": 8,
    "solar_kwh": 27.96,
    "load_kwh": 32.31,
    "import_kwh": 12.09,
    "export_kwh": 6.08,
    "self_consumed_kwh": 21.88
  },
  {
    "household_id": "small_family_high",
    "household_type": "small_family",
    "wealth": "high",
    "day": 9,
    "solar_kwh": 8.26,
    "load_kwh": 30.39,
    "import_kwh": 22.88,
    "export_kwh": 0.0,
    "self_consumed_kwh": 8.26
  },
  {
    "household_id": "small_family_high",
    "household_type": "small_family",
    "wealth": "high",
    "day": 10,
    "solar_kwh": 19.9,
    "load_kwh": 34.01,
    "import_kwh": 15.89,
    "export_kwh": 0.0,
    "self_consumed_kwh": 19.9
  },
  {
    "household_id": "small_family_high",
    "household_type": "small_family",
    "wealth": "high",
    "day": 11,
    "solar_kwh": 8.44,
    "load_kwh": 35.86,
    "import_kwh": 28.18,
    "export_kwh": 0.0,
    "self_consumed_kwh": 8.44
  },
  {
    "household_id": "small_family_high",
    "household_type": "small_family",
    "wealth": "high",
    "day": 12,
    "solar_kwh": 18.92,
    "load_kwh": 30.62,
    "import_kwh": 13.4,
    "export_kwh": 0.0,
    "self_consumed_kwh": 18.92
  },
  {
    "household_id": "small_family_high",
    "household_type": "small_family",
    "wealth": "high",
    "day": 13,
    "solar_kwh": 0.0,
    "load_kwh": 30.25,
    "import_kwh": 30.25,
    "export_kwh": 0.0,
    "self_consumed_kwh": 0.0
  },
  {
    "household_id": "small_family_high",
    "household_type": "small_family",
    "wealth": "high",
    "day": 14,
    "solar_kwh": 0.0,
    "load_kwh": 31.14,
    "import_kwh": 31.14,
    "export_kwh": 0.0,
    "self_consumed_kwh": 0.0
  },
  {
    "household_id": "small_family_high",
    "household_type": "small_family",
    "wealth": "high",
    "day": 15,
    "solar_kwh": 0.0,
    "load_kwh": 37.92,
    "import_kwh": 37.92,
    "export_kwh": 0.0,
    "self_consumed_kwh": 0.0
  },
  {
    "household_id": "small_family_high",
    "household_type": "small_family",
    "wealth": "high",
    "day": 16,
    "solar_kwh": 16.89,
    "load_kwh": 35.23,
    "import_kwh": 19.86,
    "export_kwh": 0.0,
    "self_consumed_kwh": 16.89
  },
  {
    "household_id": "small_family_high",
    "household_type": "small_family",
    "wealth": "high",
    "day": 17,
    "solar_kwh": 33.49,
    "load_kwh": 35.72,
    "import_kwh": 17.19,
    "export_kwh": 13.54,
    "self_consumed_kwh": 19.95
  },
  {
    "household_id": "small_family_high",
    "household_type": "small_family",
    "wealth": "high",
    "day": 18,
    "solar_kwh": 20.13,
    "load_kwh": 29.1,
    "import_kwh": 10.71,
    "export_kwh": 0.0,
    "self_consumed_kwh": 20.13
  },
  {
    "household_id": "small_family_high",
    "household_type": "small_family",
    "wealth": "high",
    "day": 19,
    "solar_kwh": 10.51,
    "load_kwh": 33.85,
    "import_kwh": 24.29,
    "export_kwh": 0.0,
    "self_consumed_kwh": 10.51
  },
  {
    "household_id": "small_family_high",
    "household_type": "small_family",
    "wealth": "high",
    "day": 20,
    "solar_kwh": 12.9,
    "load_kwh": 31.86,
    "import_kwh": 20.12,
    "export_kwh": 0.0,
    "self_consumed_kwh": 12.9
  },
  {
    "household_id": "small_family_high",
    "household_type": "small_family",
    "wealth": "high",
    "day": 21,
    "solar_kwh": 20.87,
    "load_kwh": 34.2,
    "import_kwh": 15.21,
    "export_kwh": 0.0,
    "self_consumed_kwh": 20.87
  },
  {
    "household_id": "small_family_high",
    "household_type": "small_family",
    "wealth": "high",
    "day": 22,
    "solar_kwh": 7.67,
    "load_kwh": 28.19,
    "import_kwh": 21.21,
    "export_kwh": 0.0,
    "self_consumed_kwh": 7.67
  },
  {
    "household_id": "small_family_high",
    "household_type": "small_family",
    "wealth": "high",
    "day": 23,
    "solar_kwh": 10.1,
    "load_kwh": 25.75,
    "import_kwh": 16.56,
    "export_kwh": 0.0,
    "self_consumed_kwh": 10.1
  },
  {
    "household_id": "small_family_high",
    "household_type": "small_family",
    "wealth": "high",
    "day": 24,
    "solar_kwh": 29.52,
    "load_kwh": 34.1,
    "import_kwh": 12.46,
    "export_kwh": 6.11,
    "self_consumed_kwh": 23.4
  },
  {
    "household_id": "small_family_high",
    "household_type": "small_family",
    "wealth": "high",
    "day": 25,
    "solar_kwh": 7.54,
    "load_kwh": 25.57,
    "import_kwh": 18.7,
    "export_kwh": 0.0,
    "self_consumed_kwh": 7.54
  },
  {
    "household_id": "small_family_high",
    "household_type": "small_family",
    "wealth": "high",
    "day": 26,
    "solar_kwh": 13.41,
    "load_kwh": 25.93,
    "import_kwh": 13.73,
    "export_kwh": 0.0,
    "self_consumed_kwh": 13.41
  },
  {
    "household_id": "small_family_high",
    "household_type": "small_family",
    "wealth": "high",
    "day": 27,
    "solar_kwh": 20.81,
    "load_kwh": 27.69,
    "import_kwh": 9.34,
    "export_kwh": 0.83,
    "self_consumed_kwh": 19.98
  },
  {
    "household_id": "small_family_high",
    "household_type": "small_family",
    "wealth": "high",
    "day": 28,
    "solar_kwh": 4.89,
    "load_kwh": 32.92,
    "import_kwh": 28.48,
    "export_kwh": 0.0,
    "self_consumed_kwh": 4.89
  },
  {
    "household_id": "small_family_high",
    "household_type": "small_family",
    "wealth": "high",
    "day": 29,
    "solar_kwh": 0.0,
    "load_kwh": 29.82,
    "import_kwh": 29.82,
    "export_kwh": 0.0,
    "self_consumed_kwh": 0.0
  },
  {
    "household_id": "small_family_high",
    "household_type": "small_family",
    "wealth": "high",
    "day": 30,
    "solar_kwh": 2.42,
    "load_kwh": 36.01,
    "import_kwh": 33.81,
    "export_kwh": 0.0,
    "self_consumed_kwh": 2.42
  },
  {
    "household_id": "small_family_middle",
    "household_type": "small_family",
    "wealth": "middle",
    "day": 1,
    "solar_kwh": 4.21,
    "load_kwh": 24.78,
    "import_kwh": 15.48,
    "export_kwh": 0.0,
    "self_consumed_kwh": 4.21
  },
  {
    "household_id": "small_family_middle",
    "household_type": "small_family",
    "wealth": "middle",
    "day": 2,
    "solar_kwh": 17.32,
    "load_kwh": 23.92,
    "import_kwh": 8.16,
    "export_kwh": 0.0,
    "self_consumed_kwh": 17.32
  },
  {
    "household_id": "small_family_middle",
    "household_type": "small_family",
    "wealth": "middle",
    "day": 3,
    "solar_kwh": 15.3,
    "load_kwh": 33.25,
    "import_kwh": 19.33,
    "export_kwh": 0.0,
    "self_consumed_kwh": 15.3
  },
  {
    "household_id": "small_family_middle",
    "household_type": "small_family",
    "wealth": "middle",
    "day": 4,
    "solar_kwh": 7.85,
    "load_kwh": 27.29,
    "import_kwh": 20.14,
    "export_kwh": 0.0,
    "self_consumed_kwh": 7.85
  },
  {
    "household_id": "small_family_middle",
    "household_type": "small_family",
    "wealth": "middle",
    "day": 5,
    "solar_kwh": 7.81,
    "load_kwh": 26.52,
    "import_kwh": 19.42,
    "export_kwh": 0.0,
    "self_consumed_kwh": 7.81
  },
  {
    "household_id": "small_family_middle",
    "household_type": "small_family",
    "wealth": "middle",
    "day": 6,
    "solar_kwh": 10.66,
    "load_kwh": 28.98,
    "import_kwh": 19.28,
    "export_kwh": 0.0,
    "self_consumed_kwh": 10.66
  },
  {
    "household_id": "small_family_middle",
    "household_type": "small_family",
    "wealth": "middle",
    "day": 7,
    "solar_kwh": 7.37,
    "load_kwh": 26.08,
    "import_kwh": 19.37,
    "export_kwh": 0.0,
    "self_consumed_kwh": 7.37
  },
  {
    "household_id": "small_family_middle",
    "household_type": "small_family",
    "wealth": "middle",
    "day": 8,
    "solar_kwh": 27.96,
    "load_kwh": 19.57,
    "import_kwh": 1.95,
    "export_kwh": 8.75,
    "self_consumed_kwh": 19.2
  },
  {
    "household_id": "small_family_middle",
    "household_type": "small_family",
    "wealth": "middle",
    "day": 9,
    "solar_kwh": 8.26,
    "load_kwh": 26.75,
    "import_kwh": 19.14,
    "export_kwh": 0.0,
    "self_consumed_kwh": 8.26
  },
  {
    "household_id": "small_family_middle",
    "household_type": "small_family",
    "wealth": "middle",
    "day": 10,
    "solar_kwh": 19.9,
    "load_kwh": 22.02,
    "import_kwh": 4.1,
    "export_kwh": 0.34,
    "self_consumed_kwh": 19.57
  },
  {
    "household_id": "small_family_middle",
    "household_type": "small_family",
    "wealth": "middle",
    "day": 11,
    "solar_kwh": 8.44,
    "load_kwh": 21.97,
    "import_kwh": 14.29,
    "export_kwh": 0.0,
    "self_consumed_kwh": 8.44
  },
  {
    "household_id": "small_family_middle",
    "household_type": "small_family",
    "wealth": "middle",
    "day": 12,
    "solar_kwh": 18.92,
    "load_kwh": 26.7,
    "import_kwh": 9.48,
    "export_kwh": 0.0,
    "self_consumed_kwh": 18.92
  },
  {
    "household_id": "small_family_middle",
    "household_type": "small_family",
    "wealth": "middle",
    "day": 13,
    "solar_kwh": 4.01,
    "load_kwh": 25.52,
    "import_kwh": 21.87,
    "export_kwh": 0.0,
    "self_consumed_kwh": 4.01
  },
  {
    "household_id": "small_family_middle",
    "household_type": "small_family",
    "wealth": "middle",
    "day": 14,
    "solar_kwh": 3.93,
    "load_kwh": 21.75,
    "import_kwh": 18.18,
    "export_kwh": 0.0,
    "self_consumed_kwh": 3.93
  },
  {
    "household_id": "small_family_middle",
    "household_type": "small_family",
    "wealth": "middle",
    "day": 15,
    "solar_kwh": 5.19,
    "load_kwh": 28.51,
    "import_kwh": 23.79,
    "export_kwh": 0.0,
    "self_consumed_kwh": 5.19
  },
  {
    "household_id": "small_family_middle",
    "household_type": "small_family",
    "wealth": "middle",
    "day": 16,
    "solar_kwh": 16.89,
    "load_kwh": 28.75,
    "import_kwh": 13.38,
    "export_kwh": 0.0,
    "self_consumed_kwh": 16.89
  },
  {
    "household_id": "small_family_middle",
    "household_type": "small_family",
    "wealth": "middle",
    "day": 17,
    "solar_kwh": 33.49,
    "load_kwh": 27.84,
    "import_kwh": 10.69,
    "export_kwh": 14.98,
    "self_consumed_kwh": 18.51
  },
  {
    "household_id": "small_family_middle",
    "household_type": "small_family",
    "wealth": "middle",
    "day": 18,
    "solar_kwh": 20.13,
    "load_kwh": 27.38,
    "import_kwh": 10.51,
    "export_kwh": 1.72,
    "self_consumed_kwh": 18.41
  },
  {
    "household_id": "small_family_middle",
    "household_type": "small_family",
    "wealth": "middle",
    "day": 19,
    "solar_kwh": 10.51,
    "load_kwh": 30.97,
    "import_kwh": 21.41,
    "export_kwh": 0.0,
    "self_consumed_kwh": 10.51
  },
  {
    "household_id": "small_family_middle",
    "household_type": "small_family",
    "wealth": "middle",
    "day": 20,
    "solar_kwh": 12.9,
    "load_kwh": 27.23,
    "import_kwh": 15.5,
    "export_kwh": 0.0,
    "self_consumed_kwh": 12.9
  },
  {
    "household_id": "small_family_middle",
    "household_type": "small_family",
    "wealth": "middle",
    "day": 21,
    "solar_kwh": 20.87,
    "load_kwh": 21.3,
    "import_kwh": 3.83,
    "export_kwh": 1.92,
    "self_consumed_kwh": 18.95
  },
  {
    "household_id": "small_family_middle",
    "household_type": "small_family",
    "wealth": "middle",
    "day": 22,
    "solar_kwh": 7.67,
    "load_kwh": 23.34,
    "import_kwh": 16.36,
    "export_kwh": 0.0,
    "self_consumed_kwh": 7.67
  },
  {
    "household_id": "small_family_middle",
    "household_type": "small_family",
    "wealth": "middle",
    "day": 23,
    "solar_kwh": 10.1,
    "load_kwh": 29.48,
    "import_kwh": 20.29,
    "export_kwh": 0.0,
    "self_consumed_kwh": 10.1
  },
  {
    "household_id": "small_family_middle",
    "household_type": "small_family",
    "wealth": "middle",
    "day": 24,
    "solar_kwh": 29.52,
    "load_kwh": 27.57,
    "import_kwh": 8.09,
    "export_kwh": 8.61,
    "self_consumed_kwh": 20.91
  },
  {
    "household_id": "small_family_middle",
    "household_type": "small_family",
    "wealth": "middle",
    "day": 25,
    "solar_kwh": 7.54,
    "load_kwh": 27.12,
    "import_kwh": 20.26,
    "export_kwh": 0.0,
    "self_consumed_kwh": 7.54
  },
  {
    "household_id": "small_family_middle",
    "household_type": "small_family",
    "wealth": "middle",
    "day": 26,
    "solar_kwh": 13.41,
    "load_kwh": 28.72,
    "import_kwh": 16.52,
    "export_kwh": 0.0,
    "self_consumed_kwh": 13.41
  },
  {
    "household_id": "small_family_middle",
    "household_type": "small_family",
    "wealth": "middle",
    "day": 27,
    "solar_kwh": 20.81,
    "load_kwh": 28.23,
    "import_kwh": 10.56,
    "export_kwh": 1.6,
    "self_consumed_kwh": 19.21
  },
  {
    "household_id": "small_family_middle",
    "household_type": "small_family",
    "wealth": "middle",
    "day": 28,
    "solar_kwh": 4.89,
    "load_kwh": 30.49,
    "import_kwh": 26.05,
    "export_kwh": 0.0,
    "self_consumed_kwh": 4.89
  },
  {
    "household_id": "small_family_middle",
    "household_type": "small_family",
    "wealth": "middle",
    "day": 29,
    "solar_kwh": 20.8,
    "load_kwh": 22.16,
    "import_kwh": 4.81,
    "export_kwh": 1.86,
    "self_consumed_kwh": 18.94
  },
  {
    "household_id": "small_family_middle",
    "household_type": "small_family",
    "wealth": "middle",
    "day": 30,
    "solar_kwh": 24.19,
    "load_kwh": 27.88,
    "import_kwh": 9.57,
    "export_kwh": 4.34,
    "self_consumed_kwh": 19.84
  },
  {
    "household_id": "studio_low",
    "household_type": "studio",
    "wealth": "low",
    "day": 1,
    "solar_kwh": 4.21,
    "load_kwh": 13.8,
    "import_kwh": 4.5,
    "export_kwh": 0.0,
    "self_consumed_kwh": 4.21
  },
  {
    "household_id": "studio_low",
    "household_type": "studio",
    "wealth": "low",
    "day": 2,
    "solar_kwh": 17.32,
    "load_kwh": 10.01,
    "import_kwh": 1.32,
    "export_kwh": 1.5,
    "self_consumed_kwh": 15.83
  },
  {
    "household_id": "studio_low",
    "household_type": "studio",
    "wealth": "low",
    "day": 3,
    "solar_kwh": 15.3,
    "load_kwh": 11.29,
    "import_kwh": 0.94,
    "export_kwh": 5.75,
    "self_consumed_kwh": 9.54
  },
  {
    "household_id": "studio_low",
    "household_type": "studio",
    "wealth": "low",
    "day": 4,
    "solar_kwh": 7.85,
    "load_kwh": 10.93,
    "import_kwh": 1.01,
    "export_kwh": 0.0,
    "self_consumed_kwh": 7.85
  },
  {
    "household_id": "studio_low",
    "household_type": "studio",
    "wealth": "low",
    "day": 5,
    "solar_kwh": 7.81,
    "load_kwh": 9.48,
    "import_kwh": 0.96,
    "export_kwh": 0.0,
    "self_consumed_kwh": 7.81
  },
  {
    "household_id": "studio_low",
    "household_type": "studio",
    "wealth": "low",
    "day": 6,
    "solar_kwh": 10.66,
    "load_kwh": 10.18,
    "import_kwh": 1.07,
    "export_kwh": 0.0,
    "self_consumed_kwh": 10.66
  },
  {
    "household_id": "studio_low",
    "household_type": "studio",
    "wealth": "low",
    "day": 7,
    "solar_kwh": 7.37,
    "load_kwh": 11.35,
    "import_kwh": 4.04,
    "export_kwh": 0.0,
    "self_consumed_kwh": 7.37
  },
  {
    "household_id": "studio_low",
    "household_type": "studio",
    "wealth": "low",
    "day": 8,
    "solar_kwh": 27.96,
    "load_kwh": 10.68,
    "import_kwh": 0.96,
    "export_kwh": 12.08,
    "self_consumed_kwh": 15.88
  },
  {
    "household_id": "studio_low",
    "household_type": "studio",
    "wealth": "low",
    "day": 9,
    "solar_kwh": 8.26,
    "load_kwh": 11.56,
    "import_kwh": 1.07,
    "export_kwh": 0.0,
    "self_consumed_kwh": 8.26
  },
  {
    "household_id": "studio_low",
    "household_type": "studio",
    "wealth": "low",
    "day": 10,
    "solar_kwh": 19.9,
    "load_kwh": 14.75,
    "import_kwh": 1.25,
    "export_kwh": 4.82,
    "self_consumed_kwh": 15.09
  },
  {
    "household_id": "studio_low",
    "household_type": "studio",
    "wealth": "low",
    "day": 11,
    "solar_kwh": 8.44,
    "load_kwh": 9.07,
    "import_kwh": 0.82,
    "export_kwh": 0.0,
    "self_consumed_kwh": 8.44
  },
  {
    "household_id": "studio_low",
    "household_type": "studio",
    "wealth": "low",
    "day": 12,
    "solar_kwh": 18.92,
    "load_kwh": 10.23,
    "import_kwh": 0.8,
    "export_kwh": 4.98,
    "self_consumed_kwh": 13.94
  },
  {
    "household_id": "studio_low",
    "household_type": "studio",
    "wealth": "low",
    "day": 13,
    "solar_kwh": 4.01,
    "load_kwh": 12.27,
    "import_kwh": 3.65,
    "export_kwh": 0.0,
    "self_consumed_kwh": 4.01
  },
  {
    "household_id": "studio_low",
    "household_type": "studio",
    "wealth": "low",
    "day": 14,
    "solar_kwh": 3.93,
    "load_kwh": 11.78,
    "import_kwh": 8.2,
    "export_kwh": 0.0,
    "self_consumed_kwh": 3.93
  },
  {
    "household_id": "studio_low",
    "household_type": "studio",
    "wealth": "low",
    "day": 15,
    "solar_kwh": 5.19,
    "load_kwh": 10.1,
    "import_kwh": 5.37,
    "export_kwh": 0.0,
    "self_consumed_kwh": 5.19
  },
  {
    "household_id": "studio_low",
    "household_type": "studio",
    "wealth": "low",
    "day": 16,
    "solar_kwh": 16.89,
    "load_kwh": 12.9,
    "import_kwh": 1.51,
    "export_kwh": 0.71,
    "self_consumed_kwh": 16.18
  },
  {
    "household_id": "studio_low",
    "household_type": "studio",
    "wealth": "low",
    "day": 17,
    "solar_kwh": 33.49,
    "load_kwh": 11.37,
    "import_kwh": 0.74,
    "export_kwh": 19.58,
    "self_consumed_kwh": 13.92
  },
  {
    "household_id": "studio_low",
    "household_type": "studio",
    "wealth": "low",
    "day": 18,
    "solar_kwh": 20.13,
    "load_kwh": 12.54,
    "import_kwh": 1.06,
    "export_kwh": 11.37,
    "self_consumed_kwh": 8.76
  },
  {
    "household_id": "studio_low",
    "household_type": "studio",
    "wealth": "low",
    "day": 19,
    "solar_kwh": 10.51,
    "load_kwh": 6.84,
    "import_kwh": 0.58,
    "export_kwh": 0.0,
    "self_consumed_kwh": 10.51
  },
  {
    "household_id": "studio_low",
    "household_type": "studio",
    "wealth": "low",
    "day": 20,
    "solar_kwh": 12.9,
    "load_kwh": 13.23,
    "import_kwh": 1.13,
    "export_kwh": 2.28,
    "self_consumed_kwh": 10.62
  },
  {
    "household_id": "studio_low",
    "household_type": "studio",
    "wealth": "low",
    "day": 21,
    "solar_kwh": 20.87,
    "load_kwh": 10.55,
    "import_kwh": 0.79,
    "export_kwh": 7.78,
    "self_consumed_kwh": 13.09
  },
  {
    "household_id": "studio_low",
    "household_type": "studio",
    "wealth": "low",
    "day": 22,
    "solar_kwh": 7.67,
    "load_kwh": 11.73,
    "import_kwh": 1.1,
    "export_kwh": 0.0,
    "self_consumed_kwh": 7.67
  },
  {
    "household_id": "studio_low",
    "household_type": "studio",
    "wealth": "low",
    "day": 23,
    "solar_kwh": 10.1,
    "load_kwh": 8.03,
    "import_kwh": 0.7,
    "export_kwh": 0.0,
    "self_consumed_kwh": 10.1
  },
  {
    "household_id": "studio_low",
    "household_type": "studio",
    "wealth": "low",
    "day": 24,
    "solar_kwh": 29.52,
    "load_kwh": 12.13,
    "import_kwh": 0.99,
    "export_kwh": 18.29,
    "self_consumed_kwh": 11.23
  },
  {
    "household_id": "studio_low",
    "household_type": "studio",
    "wealth": "low",
    "day": 25,
    "solar_kwh": 7.54,
    "load_kwh": 12.73,
    "import_kwh": 2.9,
    "export_kwh": 0.0,
    "self_consumed_kwh": 7.54
  },
  {
    "household_id": "studio_low",
    "household_type": "studio",
    "wealth": "low",
    "day": 26,
    "solar_kwh": 13.41,
    "load_kwh": 7.63,
    "import_kwh": 0.8,
    "export_kwh": 0.01,
    "self_consumed_kwh": 13.4
  },
  {
    "household_id": "studio_low",
    "household_type": "studio",
    "wealth": "low",
    "day": 27,
    "solar_kwh": 20.81,
    "load_kwh": 12.06,
    "import_kwh": 0.93,
    "export_kwh": 10.16,
    "self_consumed_kwh": 10.66
  },
  {
    "household_id": "studio_low",
    "household_type": "studio",
    "wealth": "low",
    "day": 28,
    "solar_kwh": 4.89,
    "load_kwh": 10.37,
    "import_kwh": 1.82,
    "export_kwh": 0.0,
    "self_consumed_kwh": 4.89
  },
  {
    "household_id": "studio_low",
    "household_type": "studio",
    "wealth": "low",
    "day": 29,
    "solar_kwh": 20.8,
    "load_kwh": 14.83,
    "import_kwh": 1.59,
    "export_kwh": 4.54,
    "self_consumed_kwh": 16.26
  },
  {
    "household_id": "studio_low",
    "household_type": "studio",
    "wealth": "low",
    "day": 30,
    "solar_kwh": 24.19,
    "load_kwh": 12.38,
    "import_kwh": 0.89,
    "export_kwh": 9.38,
    "self_consumed_kwh": 14.81
  },
  {
    "household_id": "studio_middle",
    "household_type": "studio",
    "wealth": "middle",
    "day": 1,
    "solar_kwh": 4.21,
    "load_kwh": 12.34,
    "import_kwh": 3.04,
    "export_kwh": 0.0,
    "self_consumed_kwh": 4.21
  },
  {
    "household_id": "studio_middle",
    "household_type": "studio",
    "wealth": "middle",
    "day": 2,
    "solar_kwh": 17.32,
    "load_kwh": 14.16,
    "import_kwh": 1.78,
    "export_kwh": 1.53,
    "self_consumed_kwh": 15.79
  },
  {
    "household_id": "studio_middle",
    "household_type": "studio",
    "wealth": "middle",
    "day": 3,
    "solar_kwh": 15.3,
    "load_kwh": 12.89,
    "import_kwh": 1.07,
    "export_kwh": 1.27,
    "self_consumed_kwh": 14.02
  },
  {
    "household_id": "studio_middle",
    "household_type": "studio",
    "wealth": "middle",
    "day": 4,
    "solar_kwh": 7.85,
    "load_kwh": 10.3,
    "import_kwh": 0.95,
    "export_kwh": 0.0,
    "self_consumed_kwh": 7.85
  },
  {
    "household_id": "studio_middle",
    "household_type": "studio",
    "wealth": "middle",
    "day": 5,
    "solar_kwh": 7.81,
    "load_kwh": 16.78,
    "import_kwh": 8.82,
    "export_kwh": 0.0,
    "self_consumed_kwh": 7.81
  },
  {
    "household_id": "studio_middle",
    "household_type": "studio",
    "wealth": "middle",
    "day": 6,
    "solar_kwh": 10.66,
    "load_kwh": 10.05,
    "import_kwh": 1.12,
    "export_kwh": 0.0,
    "self_consumed_kwh": 10.66
  },
  {
    "household_id": "studio_middle",
    "household_type": "studio",
    "wealth": "middle",
    "day": 7,
    "solar_kwh": 7.37,
    "load_kwh": 14.15,
    "import_kwh": 6.68,
    "export_kwh": 0.0,
    "self_consumed_kwh": 7.37
  },
  {
    "household_id": "studio_middle",
    "household_type": "studio",
    "wealth": "middle",
    "day": 8,
    "solar_kwh": 0.0,
    "load_kwh": 13.89,
    "import_kwh": 13.89,
    "export_kwh": 0.0,
    "self_consumed_kwh": 0.0
  },
  {
    "household_id": "studio_middle",
    "household_type": "studio",
    "wealth": "middle",
    "day": 9,
    "solar_kwh": 0.0,
    "load_kwh": 11.54,
    "import_kwh": 11.54,
    "export_kwh": 0.0,
    "self_consumed_kwh": 0.0
  },
  {
    "household_id": "studio_middle",
    "household_type": "studio",
    "wealth": "middle",
    "day": 10,
    "solar_kwh": 13.79,
    "load_kwh": 13.74,
    "import_kwh": 2.32,
    "export_kwh": 0.09,
    "self_consumed_kwh": 13.71
  },
  {
    "household_id": "studio_middle",
    "household_type": "studio",
    "wealth": "middle",
    "day": 11,
    "solar_kwh": 8.44,
    "load_kwh": 17.49,
    "import_kwh": 8.76,
    "export_kwh": 0.0,
    "self_consumed_kwh": 8.44
  },
  {
    "household_id": "studio_middle",
    "household_type": "studio",
    "wealth": "middle",
    "day": 12,
    "solar_kwh": 18.92,
    "load_kwh": 12.56,
    "import_kwh": 1.19,
    "export_kwh": 2.86,
    "self_consumed_kwh": 16.06
  },
  {
    "household_id": "studio_middle",
    "household_type": "studio",
    "wealth": "middle",
    "day": 13,
    "solar_kwh": 4.01,
    "load_kwh": 14.4,
    "import_kwh": 7.4,
    "export_kwh": 0.0,
    "self_consumed_kwh": 4.01
  },
  {
    "household_id": "studio_middle",
    "household_type": "studio",
    "wealth": "middle",
    "day": 14,
    "solar_kwh": 3.93,
    "load_kwh": 13.69,
    "import_kwh": 10.11,
    "export_kwh": 0.0,
    "self_consumed_kwh": 3.93
  },
  {
    "household_id": "studio_middle",
    "household_type": "studio",
    "wealth": "middle",
    "day": 15,
    "solar_kwh": 5.19,
    "load_kwh": 10.58,
    "import_kwh": 5.86,
    "export_kwh": 0.0,
    "self_consumed_kwh": 5.19
  },
  {
    "household_id": "studio_middle",
    "household_type": "studio",
    "wealth": "middle",
    "day": 16,
    "solar_kwh": 16.89,
    "load_kwh": 14.64,
    "import_kwh": 1.45,
    "export_kwh": 0.58,
    "self_consumed_kwh": 16.3
  },
  {
    "household_id": "studio_middle",
    "household_type": "studio",
    "wealth": "middle",
    "day": 17,
    "solar_kwh": 33.49,
    "load_kwh": 11.09,
    "import_kwh": 0.79,
    "export_kwh": 18.77,
    "self_consumed_kwh": 14.72
  },
  {
    "household_id": "studio_middle",
    "household_type": "studio",
    "wealth": "middle",
    "day": 18,
    "solar_kwh": 20.13,
    "load_kwh": 12.19,
    "import_kwh": 0.99,
    "export_kwh": 9.7,
    "self_consumed_kwh": 10.43
  },
  {
    "household_id": "studio_middle",
    "household_type": "studio",
    "wealth": "middle",
    "day": 19,
    "solar_kwh": 10.51,
    "load_kwh": 13.96,
    "import_kwh": 1.29,
    "export_kwh": 0.0,
    "self_consumed_kwh": 10.51
  },
  {
    "household_id": "studio_middle",
    "household_type": "studio",
    "wealth": "middle",
    "day": 20,
    "solar_kwh": 12.9,
    "load_kwh": 16.53,
    "import_kwh": 4.48,
    "export_kwh": 0.0,
    "self_consumed_kwh": 12.9
  },
  {
    "household_id": "studio_middle",
    "household_type": "studio",
    "wealth": "middle",
    "day": 21,
    "solar_kwh": 20.87,
    "load_kwh": 13.74,
    "import_kwh": 1.32,
    "export_kwh": 4.32,
    "self_consumed_kwh": 16.55
  },
  {
    "household_id": "studio_middle",
    "household_type": "studio",
    "wealth": "middle",
    "day": 22,
    "solar_kwh": 7.67,
    "load_kwh": 14.18,
    "import_kwh": 4.5,
    "export_kwh": 0.0,
    "self_consumed_kwh": 7.67
  },
  {
    "household_id": "studio_middle",
    "household_type": "studio",
    "wealth": "middle",
    "day": 23,
    "solar_kwh": 10.1,
    "load_kwh": 12.78,
    "import_kwh": 3.58,
    "export_kwh": 0.0,
    "self_consumed_kwh": 10.1
  },
  {
    "household_id": "studio_middle",
    "household_type": "studio",
    "wealth": "middle",
    "day": 24,
    "solar_kwh": 29.52,
    "load_kwh": 13.96,
    "import_kwh": 1.7,
    "export_kwh": 13.57,
    "self_consumed_kwh": 15.94
  },
  {
    "household_id": "studio_middle",
    "household_type": "studio",
    "wealth": "middle",
    "day": 25,
    "solar_kwh": 7.54,
    "load_kwh": 15.69,
    "import_kwh": 6.45,
    "export_kwh": 0.0,
    "self_consumed_kwh": 7.54
  },
  {
    "household_id": "studio_middle",
    "household_type": "studio",
    "wealth": "middle",
    "day": 26,
    "solar_kwh": 13.41,
    "load_kwh": 17.1,
    "import_kwh": 4.9,
    "export_kwh": 0.0,
    "self_consumed_kwh": 13.41
  },
  {
    "household_id": "studio_middle",
    "household_type": "studio",
    "wealth": "middle",
    "day": 27,
    "solar_kwh": 20.81,
    "load_kwh": 17.24,
    "import_kwh": 2.23,
    "export_kwh": 3.67,
    "self_consumed_kwh": 17.15
  },
  {
    "household_id": "studio_middle",
    "household_type": "studio",
    "wealth": "middle",
    "day": 28,
    "solar_kwh": 4.89,
    "load_kwh": 10.91,
    "import_kwh": 5.72,
    "export_kwh": 0.0,
    "self_consumed_kwh": 4.89
  },
  {
    "household_id": "studio_middle",
    "household_type": "studio",
    "wealth": "middle",
    "day": 29,
    "solar_kwh": 20.8,
    "load_kwh": 15.27,
    "import_kwh": 2.29,
    "export_kwh": 4.44,
    "self_consumed_kwh": 16.35
  },
  {
    "household_id": "studio_middle",
    "household_type": "studio",
    "wealth": "middle",
    "day": 30,
    "solar_kwh": 24.19,
    "load_kwh": 11.87,
    "import_kwh": 0.89,
    "export_kwh": 8.78,
    "self_consumed_kwh": 15.41
  }
]